[
    {
        "no": "74093",
        "title": "[네이버페이] 스토어 방문 1원 받으세요 (순수식품)",
        "link": "https://www.ppomppu.co.kr/zboard/view.php?id=coupon&page=1&divpage=13&search_type=subject&keyword=%B3%D7%C0%CC%B9%F6&no=74093"
    },
    {
        "no": "74203",
        "title": "[네이버페이] 참존 스토어찜 80원",
        "link": "https://www.ppomppu.co.kr/zboard/view.php?id=coupon&page=1&divpage=13&search_type=subject&keyword=%B3%D7%C0%CC%B9%F6&no=74203"
    },
    {
        "no": "74202",
        "title": "[네이버페이] 라피타 인스타그램 팔로우 240원 받으세요 (& 메디플라워 스토어 방문)",
        "link": "https://www.ppomppu.co.kr/zboard/view.php?id=coupon&page=1&divpage=13&search_type=subject&keyword=%B3%D7%C0%CC%B9%F6&no=74202"
    },
    {
        "no": "74201",
        "title": "[네이버페이] 슬림9 스토어찜 50원 받으세요 (재오픈)",
        "link": "https://www.ppomppu.co.kr/zboard/view.php?id=coupon&page=1&divpage=13&search_type=subject&keyword=%B3%D7%C0%CC%B9%F6&no=74201"
    },
    {
        "no": "74194",
        "title": "[네이버페이] 나이키 24원",
        "link": "https://www.ppomppu.co.kr/zboard/view.php?id=coupon&page=1&divpage=13&search_type=subject&keyword=%B3%D7%C0%CC%B9%F6&no=74194"
    },
    {
        "no": "74188",
        "title": "[네이버 페이] LH주거찾기 유튜브 구독",
        "link": "https://www.ppomppu.co.kr/zboard/view.php?id=coupon&page=1&divpage=13&search_type=subject&keyword=%B3%D7%C0%CC%B9%F6&no=74188"
    },
    {
        "no": "74177",
        "title": "(끌올)[네이버페이] 나이키 24원 외 기타등등 (라피타 인스타그램 팔로우 추가)",
        "link": "https://www.ppomppu.co.kr/zboard/view.php?id=coupon&page=1&divpage=13&search_type=subject&keyword=%B3%D7%C0%CC%B9%F6&no=74177"
    },
    {
        "no": "74160",
        "title": "[네이버페이] LIFE WITH 10원 받으세요 (나이키 기타 등등 포함)",
        "link": "https://www.ppomppu.co.kr/zboard/view.php?id=coupon&page=1&divpage=13&search_type=subject&keyword=%B3%D7%C0%CC%B9%F6&no=74160"
    },
    {
        "no": "74158",
        "title": "[네이버페이] 위메프 10원 받으세요",
        "link": "https://www.ppomppu.co.kr/zboard/view.php?id=coupon&page=1&divpage=13&search_type=subject&keyword=%B3%D7%C0%CC%B9%F6&no=74158"
    },
    {
        "no": "74157",
        "title": "[네이버페이] DB손해보험 10원 받으세요",
        "link": "https://www.ppomppu.co.kr/zboard/view.php?id=coupon&page=1&divpage=13&search_type=subject&keyword=%B3%D7%C0%CC%B9%F6&no=74157"
    },
    {
        "no": "74146",
        "title": "(끌올)[네이버페이] 나이키 24원 외 기타등등 (신한금융그룹 구독 재추가)",
        "link": "https://www.ppomppu.co.kr/zboard/view.php?id=coupon&page=1&divpage=13&search_type=subject&keyword=%B3%D7%C0%CC%B9%F6&no=74146"
    },
    {
        "no": "74136",
        "title": "[네이버페이] KB포인트리 30원 받으세요",
        "link": "https://www.ppomppu.co.kr/zboard/view.php?id=coupon&page=1&divpage=13&search_type=subject&keyword=%B3%D7%C0%CC%B9%F6&no=74136"
    },
    {
        "no": "74135",
        "title": "(끌올)[네이버페이] 나이키 24원 외 기타등등 (메디플라워 방문 추가)",
        "link": "https://www.ppomppu.co.kr/zboard/view.php?id=coupon&page=1&divpage=13&search_type=subject&keyword=%B3%D7%C0%CC%B9%F6&no=74135"
    },
    {
        "no": "74132",
        "title": "[네이버페이] KB손해보험 10원 받으세요",
        "link": "https://www.ppomppu.co.kr/zboard/view.php?id=coupon&page=1&divpage=13&search_type=subject&keyword=%B3%D7%C0%CC%B9%F6&no=74132"
    },
    {
        "no": "74114",
        "title": "[네이버페이] 아로망 스토어 방문 1원 받으세요",
        "link": "https://www.ppomppu.co.kr/zboard/view.php?id=coupon&page=1&divpage=13&search_type=subject&keyword=%B3%D7%C0%CC%B9%F6&no=74114"
    },
    {
        "no": "74110",
        "title": "[네이버페이] 스토어찜 & 방문 51원 받으세요 (아로망 & 메디플라워 방문)",
        "link": "https://www.ppomppu.co.kr/zboard/view.php?id=coupon&page=1&divpage=13&search_type=subject&keyword=%B3%D7%C0%CC%B9%F6&no=74110"
    },
    {
        "no": "74107",
        "title": "[네이버페이] 스토어찜 50원 받으세요 (메디플라워 재오픈)",
        "link": "https://www.ppomppu.co.kr/zboard/view.php?id=coupon&page=1&divpage=13&search_type=subject&keyword=%B3%D7%C0%CC%B9%F6&no=74107"
    },
    {
        "no": "74101",
        "title": "(끌올)[네이버페이] 나이키 24원 외 기타등등 (순수식품 방문, 삼성iD 팔로우 추가)",
        "link": "https://www.ppomppu.co.kr/zboard/view.php?id=coupon&page=1&divpage=13&search_type=subject&keyword=%B3%D7%C0%CC%B9%F6&no=74101"
    },
    {
        "no": "74099",
        "title": "[네이버페이] 나이키 24원 외",
        "link": "https://www.ppomppu.co.kr/zboard/view.php?id=coupon&page=1&divpage=13&search_type=subject&keyword=%B3%D7%C0%CC%B9%F6&no=74099"
    },
    {
        "no": "74094",
        "title": "[네이버페이] 삼성화재 10원 받으세요",
        "link": "https://www.ppomppu.co.kr/zboard/view.php?id=coupon&page=1&divpage=13&search_type=subject&keyword=%B3%D7%C0%CC%B9%F6&no=74094"
    }
]